Basic/6_FSM/FSM_Mealy.v
/*
该程序用于学习三段式状态机。
当输入数据为 指定序列时输入为 AA BB CC时输出1.
*/

// 状态机完全按照数学模型来写，分为三段，将结构描述清楚即可
module FSM_Mealy(           //  FSM_Moore fsm(
    input wire clk,         //      .clk  (   ),
    input wire rst_n,       //      .rst_n(   ),
    input wire [7:0] data,  //      .data (   ),
    output reg flag         //      .flag (   )
);                          //  );


// =====三段式状态机 Mealy型===== //
reg [1:0] c_state,n_state;

localparam 
    idle  =  'b00,
    aa    =  'b01,
    bb    =  'b10;

// 状态转移 时序部分
always @(posedge clk or negedge rst_n) begin
    if(~rst_n) c_state <=  idle;
    else c_state <= n_state;
end

// 状态转移条件 次态组合电路
always @(*) begin
    case(c_state)
        idle: begin
            if(data == 'haa) n_state = aa;
            else n_state = idle;
        end
        aa  : begin
            if(data == 'haa) n_state = aa;
            else if(data =='hbb) n_state = bb;
            else n_state = idle;
        end
        bb  : begin
            if(data == 'haa) n_state = aa;
            else if(data == 'hcc) n_state = idle;
            else n_state = idle;
        end
        default: n_state  =  idle;
    endcase
end

// 输出部分 组合电路
always @(*) begin
    if (c_state == bb && data == 'hcc ) flag = 1'b1;
    else flag = 1'b0;
end
endmodule

Basic/6_FSM/tb.v
`timescale 1ns/1ns
`define CLOCK_PERIOD 10
module tb();

reg clk;
reg rst_n;
always #(`CLOCK_PERIOD/2) clk<=~clk;

reg [7:0] data_i;
wire flag;

FSM_Mealy fsm(
    .clk  (clk      ),
    .rst_n(rst_n    ),
    .data (data_i   ),
    .flag (flag     )
);

initial begin
    $dumpfile("./dumpfile.vcd");
    $dumpvars;
    clk<=1'b1;
    rst_n<=1'b0;
    data_i<='hff;
    #`CLOCK_PERIOD
    rst_n<=1'b1;
    #(`CLOCK_PERIOD + 1 )
    #`CLOCK_PERIOD data_i<='haa;
    #`CLOCK_PERIOD data_i<='hbb;
    #`CLOCK_PERIOD data_i<='hcc;
    #`CLOCK_PERIOD data_i<='hbb;
    #`CLOCK_PERIOD data_i<='haa;
    #`CLOCK_PERIOD data_i<='hbb;
    #`CLOCK_PERIOD data_i<='hcc;
    #`CLOCK_PERIOD data_i<='haa;
    #`CLOCK_PERIOD data_i<='hbb;
    #`CLOCK_PERIOD data_i<='haa;
    #`CLOCK_PERIOD data_i<='hbb;
    #`CLOCK_PERIOD data_i<='hcc;
    #`CLOCK_PERIOD data_i<='hcc;
    #(`CLOCK_PERIOD * 4)
    $finish;
end

endmodule

Basic/6_FSM/dumpfile.vcd
$date
	Mon Mar 07 20:16:41 2022
$end
$version
	Icarus Verilog
$end
$timescale
	1ns
$end
$scope module tb $end
$var wire 1 ! flag $end
$var reg 1 " clk $end
$var reg 8 # data_i [7:0] $end
$var reg 1 $ rst_n $end
$scope module fsm $end
$var wire 1 " clk $end
$var wire 8 % data [7:0] $end
$var wire 1 $ rst_n $end
$var reg 2 & c_state [1:0] $end
$var reg 1 ! flag $end
$var reg 2 ' n_state [1:0] $end
$upscope $end
$upscope $end
$enddefinitions $end
#0
$dumpvars
b0 '
b0 &
b11111111 %
0$
b11111111 #
1"
0!
$end
#5
0"
#10
1"
1$
#15
0"
#20
1"
#25
0"
#30
1"
#31
b1 '
b10101010 #
b10101010 %
#35
0"
#40
b1 &
1"
#41
b10 '
b10111011 #
b10111011 %
#45
0"
#50
b0 '
b10 &
1"
#51
1!
b11001100 #
b11001100 %
#55
0"
#60
0!
b0 &
1"
#61
b10111011 #
b10111011 %
#65
0"
#70
1"
#71
b1 '
b10101010 #
b10101010 %
#75
0"
#80
b1 &
1"
#81
b10 '
b10111011 #
b10111011 %
#85
0"
#90
b0 '
b10 &
1"
#91
1!
b11001100 #
b11001100 %
#95
0"
#100
0!
b0 &
1"
#101
b1 '
b10101010 #
b10101010 %
#105
0"
#110
b1 &
1"
#111
b10 '
b10111011 #
b10111011 %
#115
0"
#120
b0 '
b10 &
1"
#121
b1 '
b10101010 #
b10101010 %
#125
0"
#130
b1 &
1"
#131
b10 '
b10111011 #
b10111011 %
#135
0"
#140
b0 '
b10 &
1"
#141
1!
b11001100 #
b11001100 %
#145
0"
#150
0!
b0 &
1"
