Basic/Freq_Divider/FD.v
`timescale 1ps/1ps
module FD (
    input wire clk_in,
    input wire [31:0] N,
    output reg clk_out
);
    initial begin
        cnt<=1'b1;
        clk_out<='b0;
    end

    reg [31:0] cnt;
    always @(edge clk_in) begin
        if (cnt<N)begin
            cnt<=1'b1+cnt;
        end else begin
            cnt<=1'b1;
            clk_out<=~clk_out;
        end
    end
endmodule

Basic/Freq_Divider/tb.v
`timescale 1ps/1ps
module tb ();
    reg clk;
    wire clk_out;
    reg [31:0] N;
    FD fd(
        .clk_in(clk),
        .N(N),
        .clk_out(clk_out)
    );
    initial begin
        $dumpfile("dumpfile.vcd");
        $dumpvars;
        clk<=1'b0;
        N<=2;
        # 30
        N<=3;
        # 30
        N<=4;
        # 30
        N<=5;
        # 30
        $finish;
    end
    
    always #1 clk<=~clk;

endmodule

Basic/Freq_Divider/dumpfile.vcd
$date
	Tue Nov 23 21:22:40 2021
$end
$version
	Icarus Verilog
$end
$timescale
	1ps
$end
$scope module tb $end
$var wire 1 ! clk_out $end
$var reg 32 " N [31:0] $end
$var reg 1 # clk $end
$scope module fd $end
$var wire 32 $ N [31:0] $end
$var wire 1 # clk_in $end
$var reg 1 ! clk_out $end
$var reg 32 % cnt [31:0] $end
$upscope $end
$upscope $end
$enddefinitions $end
#0
$dumpvars
b10 %
b10 $
0#
b10 "
0!
$end
#1
1!
b1 %
1#
#2
b10 %
0#
#3
0!
b1 %
1#
#4
b10 %
0#
#5
1!
b1 %
1#
#6
b10 %
0#
#7
0!
b1 %
1#
#8
b10 %
0#
#9
1!
b1 %
1#
#10
b10 %
0#
#11
0!
b1 %
1#
#12
b10 %
0#
#13
1!
b1 %
1#
#14
b10 %
0#
#15
0!
b1 %
1#
#16
b10 %
0#
#17
1!
b1 %
1#
#18
b10 %
0#
#19
0!
b1 %
1#
#20
b10 %
0#
#21
1!
b1 %
1#
#22
b10 %
0#
#23
0!
b1 %
1#
#24
b10 %
0#
#25
1!
b1 %
1#
#26
b10 %
0#
#27
0!
b1 %
1#
#28
b10 %
0#
#29
1!
b1 %
1#
#30
b10 %
0#
b11 "
b11 $
#31
b11 %
1#
#32
0!
b1 %
0#
#33
b10 %
1#
#34
b11 %
0#
#35
1!
b1 %
1#
#36
b10 %
0#
#37
b11 %
1#
#38
0!
b1 %
0#
#39
b10 %
1#
#40
b11 %
0#
#41
1!
b1 %
1#
#42
b10 %
0#
#43
b11 %
1#
#44
0!
b1 %
0#
#45
b10 %
1#
#46
b11 %
0#
#47
1!
b1 %
1#
#48
b10 %
0#
#49
b11 %
1#
#50
0!
b1 %
0#
#51
b10 %
1#
#52
b11 %
0#
#53
1!
b1 %
1#
#54
b10 %
0#
#55
b11 %
1#
#56
0!
b1 %
0#
#57
b10 %
1#
#58
b11 %
0#
#59
1!
b1 %
1#
#60
b10 %
0#
b100 "
b100 $
#61
b11 %
1#
#62
b100 %
0#
#63
0!
b1 %
1#
#64
b10 %
0#
#65
b11 %
1#
#66
b100 %
0#
#67
1!
b1 %
1#
#68
b10 %
0#
#69
b11 %
1#
#70
b100 %
0#
#71
0!
b1 %
1#
#72
b10 %
0#
#73
b11 %
1#
#74
b100 %
0#
#75
1!
b1 %
1#
#76
b10 %
0#
#77
b11 %
1#
#78
b100 %
0#
#79
0!
b1 %
1#
#80
b10 %
0#
#81
b11 %
1#
#82
b100 %
0#
#83
1!
b1 %
1#
#84
b10 %
0#
#85
b11 %
1#
#86
b100 %
0#
#87
0!
b1 %
1#
#88
b10 %
0#
#89
b11 %
1#
#90
b100 %
0#
b101 "
b101 $
#91
b101 %
1#
#92
1!
b1 %
0#
#93
b10 %
1#
#94
b11 %
0#
#95
b100 %
1#
#96
b101 %
0#
#97
0!
b1 %
1#
#98
b10 %
0#
#99
b11 %
1#
#100
b100 %
0#
#101
b101 %
1#
#102
1!
b1 %
0#
#103
b10 %
1#
#104
b11 %
0#
#105
b100 %
1#
#106
b101 %
0#
#107
0!
b1 %
1#
#108
b10 %
0#
#109
b11 %
1#
#110
b100 %
0#
#111
b101 %
1#
#112
1!
b1 %
0#
#113
b10 %
1#
#114
b11 %
0#
#115
b100 %
1#
#116
b101 %
0#
#117
0!
b1 %
1#
#118
b10 %
0#
#119
b11 %
1#
#120
b100 %
0#
